gis/__init__.py
gis/protobuf/__init__.py
gis/protobuf/linestring_pb2.py
gis/protobuf/point_pb2.py
gis/protobuf/polygon_pb2.py
protobuf_gis-1.0.3.dist-info/DESCRIPTION.rst
protobuf_gis-1.0.3.dist-info/METADATA
protobuf_gis-1.0.3.dist-info/RECORD
protobuf_gis-1.0.3.dist-info/WHEEL
protobuf_gis-1.0.3.dist-info/metadata.json
protobuf_gis-1.0.3.dist-info/top_level.txt
